[{"size_y":60,"size_x":90,"name":"Lift","x":1,"y":240,"ID":"Lift1240"},{"size_y":60,"size_x":90,"name":"Lift","x":1110,"y":240,"ID":"Lift1110240"},{"size_y":60,"size_x":90,"name":"Lift","x":1,"y":300,"ID":"Lift1300"},{"size_y":60,"size_x":90,"name":"Lift","x":1110,"y":300,"ID":"Lift1110300"},{"size_y":60,"size_x":90,"name":"Port","x":0,"y":0,"ID":"Port 150-90"},{"size_y":60,"size_x":90,"name":"Port","x":0,"y":540,"ID":"Port 150-210"},{"size_y":60,"size_x":90,"name":"Port","x":1110,"y":0,"ID":"Port 600-150"},{"size_y":60,"size_x":90,"name":"Port","x":1080,"y":510,"ID":"Port 480-210"},{"size_y":150,"size_x":210,"name":"Room","x":330,"y":90,"ID":"Room15090"},{"size_y":150,"size_x":210,"name":"Room","x":330,"y":390,"ID":"Room120300"},{"size_y":150,"size_x":210,"name":"Room","x":690,"y":90,"ID":"Room510120"},{"size_y":150,"size_x":210,"name":"Room","x":720,"y":360,"ID":"Room480360"},{"name":"Node","x":2,"y":2,"direction":0},{"name":"Node","x":2,"y":32,"direction":0},{"name":"Node","x":2,"y":62,"direction":0},{"name":"Node","x":2,"y":92,"direction":0},{"name":"Node","x":2,"y":122,"direction":0},{"name":"Node","x":2,"y":152,"direction":0},{"name":"Node","x":2,"y":182,"direction":0},{"name":"Node","x":2,"y":212,"direction":0},{"name":"Node","x":2,"y":242,"direction":0},{"name":"Node","x":2,"y":272,"direction":0},{"name":"Node","x":2,"y":302,"direction":0},{"name":"Node","x":2,"y":332,"direction":0},{"name":"Node","x":2,"y":362,"direction":0},{"name":"Node","x":2,"y":392,"direction":0},{"name":"Node","x":2,"y":422,"direction":0},{"name":"Node","x":2,"y":452,"direction":0},{"name":"Node","x":2,"y":482,"direction":0},{"name":"Node","x":2,"y":512,"direction":0},{"name":"Node","x":2,"y":542,"direction":0},{"name":"Node","x":2,"y":572,"direction":0},{"name":"Node","x":32,"y":2,"direction":0},{"name":"Node","x":32,"y":32,"direction":0},{"name":"Node","x":32,"y":62,"direction":0},{"name":"Node","x":32,"y":92,"direction":0},{"name":"Node","x":32,"y":122,"direction":0},{"name":"Node","x":32,"y":152,"direction":0},{"name":"Node","x":32,"y":182,"direction":0},{"name":"Node","x":32,"y":212,"direction":0},{"name":"Node","x":32,"y":242,"direction":0},{"name":"Node","x":32,"y":272,"direction":0},{"name":"Node","x":32,"y":302,"direction":0},{"name":"Node","x":32,"y":332,"direction":0},{"name":"Node","x":32,"y":362,"direction":0},{"name":"Node","x":32,"y":392,"direction":0},{"name":"Node","x":32,"y":422,"direction":0},{"name":"Node","x":32,"y":452,"direction":0},{"name":"Node","x":32,"y":482,"direction":0},{"name":"Node","x":32,"y":512,"direction":0},{"name":"Node","x":32,"y":542,"direction":0},{"name":"Node","x":32,"y":572,"direction":0},{"name":"Node","x":62,"y":2,"direction":0},{"name":"Node","x":62,"y":32,"direction":0},{"name":"Node","x":62,"y":62,"direction":0},{"name":"Node","x":62,"y":92,"direction":0},{"name":"Node","x":62,"y":122,"direction":4},{"name":"Node","x":62,"y":152,"direction":4},{"name":"Node","x":62,"y":182,"direction":1},{"name":"Node","x":62,"y":212,"direction":0},{"name":"Node","x":62,"y":242,"direction":0},{"name":"Node","x":62,"y":272,"direction":0},{"name":"Node","x":62,"y":302,"direction":0},{"name":"Node","x":62,"y":332,"direction":0},{"name":"Node","x":62,"y":362,"direction":0},{"name":"Node","x":62,"y":392,"direction":0},{"name":"Node","x":62,"y":422,"direction":0},{"name":"Node","x":62,"y":452,"direction":0},{"name":"Node","x":62,"y":482,"direction":0},{"name":"Node","x":62,"y":512,"direction":0},{"name":"Node","x":62,"y":542,"direction":0},{"name":"Node","x":62,"y":572,"direction":0},{"name":"Node","x":92,"y":2,"direction":0},{"name":"Node","x":92,"y":32,"direction":0},{"name":"Node","x":92,"y":62,"direction":0},{"name":"Node","x":92,"y":92,"direction":0},{"name":"Node","x":92,"y":122,"direction":1},{"name":"Node","x":92,"y":152,"direction":0},{"name":"Node","x":92,"y":182,"direction":1},{"name":"Node","x":92,"y":212,"direction":0},{"name":"Node","x":92,"y":242,"direction":0},{"name":"Node","x":92,"y":272,"direction":0},{"name":"Node","x":92,"y":302,"direction":0},{"name":"Node","x":92,"y":332,"direction":0},{"name":"Node","x":92,"y":362,"direction":0},{"name":"Node","x":92,"y":392,"direction":0},{"name":"Node","x":92,"y":422,"direction":0},{"name":"Node","x":92,"y":452,"direction":0},{"name":"Node","x":92,"y":482,"direction":0},{"name":"Node","x":92,"y":512,"direction":0},{"name":"Node","x":92,"y":542,"direction":0},{"name":"Node","x":92,"y":572,"direction":0},{"name":"Node","x":122,"y":2,"direction":0},{"name":"Node","x":122,"y":32,"direction":0},{"name":"Node","x":122,"y":62,"direction":0},{"name":"Node","x":122,"y":92,"direction":0},{"name":"Node","x":122,"y":122,"direction":1},{"name":"Node","x":122,"y":152,"direction":0},{"name":"Node","x":122,"y":182,"direction":1},{"name":"Node","x":122,"y":212,"direction":0},{"name":"Node","x":122,"y":242,"direction":0},{"name":"Node","x":122,"y":272,"direction":0},{"name":"Node","x":122,"y":302,"direction":0},{"name":"Node","x":122,"y":332,"direction":0},{"name":"Node","x":122,"y":362,"direction":0},{"name":"Node","x":122,"y":392,"direction":0},{"name":"Node","x":122,"y":422,"direction":0},{"name":"Node","x":122,"y":452,"direction":0},{"name":"Node","x":122,"y":482,"direction":0},{"name":"Node","x":122,"y":512,"direction":0},{"name":"Node","x":122,"y":542,"direction":0},{"name":"Node","x":122,"y":572,"direction":0},{"name":"Node","x":152,"y":2,"direction":0},{"name":"Node","x":152,"y":32,"direction":0},{"name":"Node","x":152,"y":62,"direction":0},{"name":"Node","x":152,"y":92,"direction":0},{"name":"Node","x":152,"y":122,"direction":1},{"name":"Node","x":152,"y":152,"direction":0},{"name":"Node","x":152,"y":182,"direction":1},{"name":"Node","x":152,"y":212,"direction":0},{"name":"Node","x":152,"y":242,"direction":0},{"name":"Node","x":152,"y":272,"direction":0},{"name":"Node","x":152,"y":302,"direction":0},{"name":"Node","x":152,"y":332,"direction":0},{"name":"Node","x":152,"y":362,"direction":0},{"name":"Node","x":152,"y":392,"direction":0},{"name":"Node","x":152,"y":422,"direction":0},{"name":"Node","x":152,"y":452,"direction":0},{"name":"Node","x":152,"y":482,"direction":0},{"name":"Node","x":152,"y":512,"direction":0},{"name":"Node","x":152,"y":542,"direction":0},{"name":"Node","x":152,"y":572,"direction":0},{"name":"Node","x":182,"y":2,"direction":0},{"name":"Node","x":182,"y":32,"direction":0},{"name":"Node","x":182,"y":62,"direction":0},{"name":"Node","x":182,"y":92,"direction":0},{"name":"Node","x":182,"y":122,"direction":1},{"name":"Node","x":182,"y":152,"direction":0},{"name":"Node","x":182,"y":182,"direction":1},{"name":"Node","x":182,"y":212,"direction":0},{"name":"Node","x":182,"y":242,"direction":0},{"name":"Node","x":182,"y":272,"direction":0},{"name":"Node","x":182,"y":302,"direction":0},{"name":"Node","x":182,"y":332,"direction":0},{"name":"Node","x":182,"y":362,"direction":0},{"name":"Node","x":182,"y":392,"direction":0},{"name":"Node","x":182,"y":422,"direction":0},{"name":"Node","x":182,"y":452,"direction":0},{"name":"Node","x":182,"y":482,"direction":0},{"name":"Node","x":182,"y":512,"direction":0},{"name":"Node","x":182,"y":542,"direction":0},{"name":"Node","x":182,"y":572,"direction":0},{"name":"Node","x":212,"y":2,"direction":0},{"name":"Node","x":212,"y":32,"direction":1},{"name":"Node","x":212,"y":62,"direction":3},{"name":"Node","x":212,"y":92,"direction":3},{"name":"Node","x":212,"y":122,"direction":3},{"name":"Node","x":212,"y":152,"direction":3},{"name":"Node","x":212,"y":182,"direction":3},{"name":"Node","x":212,"y":212,"direction":3},{"name":"Node","x":212,"y":242,"direction":3},{"name":"Node","x":212,"y":272,"direction":3},{"name":"Node","x":212,"y":302,"direction":1},{"name":"Node","x":212,"y":332,"direction":0},{"name":"Node","x":212,"y":362,"direction":0},{"name":"Node","x":212,"y":392,"direction":0},{"name":"Node","x":212,"y":422,"direction":0},{"name":"Node","x":212,"y":452,"direction":0},{"name":"Node","x":212,"y":482,"direction":0},{"name":"Node","x":212,"y":512,"direction":0},{"name":"Node","x":212,"y":542,"direction":0},{"name":"Node","x":212,"y":572,"direction":0},{"name":"Node","x":242,"y":2,"direction":0},{"name":"Node","x":242,"y":32,"direction":1},{"name":"Node","x":242,"y":62,"direction":0},{"name":"Node","x":242,"y":92,"direction":0},{"name":"Node","x":242,"y":122,"direction":0},{"name":"Node","x":242,"y":152,"direction":0},{"name":"Node","x":242,"y":182,"direction":0},{"name":"Node","x":242,"y":212,"direction":0},{"name":"Node","x":242,"y":242,"direction":0},{"name":"Node","x":242,"y":272,"direction":2},{"name":"Node","x":242,"y":302,"direction":1},{"name":"Node","x":242,"y":332,"direction":0},{"name":"Node","x":242,"y":362,"direction":0},{"name":"Node","x":242,"y":392,"direction":0},{"name":"Node","x":242,"y":422,"direction":0},{"name":"Node","x":242,"y":452,"direction":0},{"name":"Node","x":242,"y":482,"direction":0},{"name":"Node","x":242,"y":512,"direction":0},{"name":"Node","x":242,"y":542,"direction":0},{"name":"Node","x":242,"y":572,"direction":0},{"name":"Node","x":272,"y":2,"direction":0},{"name":"Node","x":272,"y":32,"direction":1},{"name":"Node","x":272,"y":62,"direction":0},{"name":"Node","x":272,"y":92,"direction":0},{"name":"Node","x":272,"y":122,"direction":0},{"name":"Node","x":272,"y":152,"direction":0},{"name":"Node","x":272,"y":182,"direction":0},{"name":"Node","x":272,"y":212,"direction":0},{"name":"Node","x":272,"y":242,"direction":0},{"name":"Node","x":272,"y":272,"direction":2},{"name":"Node","x":272,"y":302,"direction":1},{"name":"Node","x":272,"y":332,"direction":0},{"name":"Node","x":272,"y":362,"direction":0},{"name":"Node","x":272,"y":392,"direction":0},{"name":"Node","x":272,"y":422,"direction":0},{"name":"Node","x":272,"y":452,"direction":0},{"name":"Node","x":272,"y":482,"direction":0},{"name":"Node","x":272,"y":512,"direction":0},{"name":"Node","x":272,"y":542,"direction":0},{"name":"Node","x":272,"y":572,"direction":0},{"name":"Node","x":302,"y":2,"direction":0},{"name":"Node","x":302,"y":32,"direction":1},{"name":"Node","x":302,"y":62,"direction":0},{"name":"Node","x":302,"y":92,"direction":0},{"name":"Node","x":302,"y":122,"direction":0},{"name":"Node","x":302,"y":152,"direction":0},{"name":"Node","x":302,"y":182,"direction":0},{"name":"Node","x":302,"y":212,"direction":0},{"name":"Node","x":302,"y":242,"direction":0},{"name":"Node","x":302,"y":272,"direction":2},{"name":"Node","x":302,"y":302,"direction":1},{"name":"Node","x":302,"y":332,"direction":0},{"name":"Node","x":302,"y":362,"direction":0},{"name":"Node","x":302,"y":392,"direction":0},{"name":"Node","x":302,"y":422,"direction":0},{"name":"Node","x":302,"y":452,"direction":0},{"name":"Node","x":302,"y":482,"direction":0},{"name":"Node","x":302,"y":512,"direction":0},{"name":"Node","x":302,"y":542,"direction":0},{"name":"Node","x":302,"y":572,"direction":0},{"name":"Node","x":332,"y":2,"direction":0},{"name":"Node","x":332,"y":32,"direction":1},{"name":"Node","x":332,"y":62,"direction":0},{"name":"Node","x":332,"y":92,"direction":0},{"name":"Node","x":332,"y":122,"direction":0},{"name":"Node","x":332,"y":152,"direction":0},{"name":"Node","x":332,"y":182,"direction":0},{"name":"Node","x":332,"y":212,"direction":0},{"name":"Node","x":332,"y":242,"direction":0},{"name":"Node","x":332,"y":272,"direction":2},{"name":"Node","x":332,"y":302,"direction":1},{"name":"Node","x":332,"y":332,"direction":0},{"name":"Node","x":332,"y":362,"direction":0},{"name":"Node","x":332,"y":392,"direction":0},{"name":"Node","x":332,"y":422,"direction":0},{"name":"Node","x":332,"y":452,"direction":0},{"name":"Node","x":332,"y":482,"direction":0},{"name":"Node","x":332,"y":512,"direction":0},{"name":"Node","x":332,"y":542,"direction":0},{"name":"Node","x":332,"y":572,"direction":0},{"name":"Node","x":362,"y":2,"direction":0},{"name":"Node","x":362,"y":32,"direction":1},{"name":"Node","x":362,"y":62,"direction":0},{"name":"Node","x":362,"y":92,"direction":0},{"name":"Node","x":362,"y":122,"direction":0},{"name":"Node","x":362,"y":152,"direction":0},{"name":"Node","x":362,"y":182,"direction":0},{"name":"Node","x":362,"y":212,"direction":0},{"name":"Node","x":362,"y":242,"direction":0},{"name":"Node","x":362,"y":272,"direction":2},{"name":"Node","x":362,"y":302,"direction":1},{"name":"Node","x":362,"y":332,"direction":0},{"name":"Node","x":362,"y":362,"direction":0},{"name":"Node","x":362,"y":392,"direction":0},{"name":"Node","x":362,"y":422,"direction":0},{"name":"Node","x":362,"y":452,"direction":0},{"name":"Node","x":362,"y":482,"direction":0},{"name":"Node","x":362,"y":512,"direction":0},{"name":"Node","x":362,"y":542,"direction":0},{"name":"Node","x":362,"y":572,"direction":0},{"name":"Node","x":392,"y":2,"direction":0},{"name":"Node","x":392,"y":32,"direction":1},{"name":"Node","x":392,"y":62,"direction":0},{"name":"Node","x":392,"y":92,"direction":0},{"name":"Node","x":392,"y":122,"direction":0},{"name":"Node","x":392,"y":152,"direction":0},{"name":"Node","x":392,"y":182,"direction":0},{"name":"Node","x":392,"y":212,"direction":0},{"name":"Node","x":392,"y":242,"direction":0},{"name":"Node","x":392,"y":272,"direction":2},{"name":"Node","x":392,"y":302,"direction":1},{"name":"Node","x":392,"y":332,"direction":0},{"name":"Node","x":392,"y":362,"direction":0},{"name":"Node","x":392,"y":392,"direction":0},{"name":"Node","x":392,"y":422,"direction":0},{"name":"Node","x":392,"y":452,"direction":0},{"name":"Node","x":392,"y":482,"direction":0},{"name":"Node","x":392,"y":512,"direction":0},{"name":"Node","x":392,"y":542,"direction":0},{"name":"Node","x":392,"y":572,"direction":0},{"name":"Node","x":422,"y":2,"direction":0},{"name":"Node","x":422,"y":32,"direction":1},{"name":"Node","x":422,"y":62,"direction":0},{"name":"Node","x":422,"y":92,"direction":0},{"name":"Node","x":422,"y":122,"direction":0},{"name":"Node","x":422,"y":152,"direction":0},{"name":"Node","x":422,"y":182,"direction":0},{"name":"Node","x":422,"y":212,"direction":0},{"name":"Node","x":422,"y":242,"direction":0},{"name":"Node","x":422,"y":272,"direction":2},{"name":"Node","x":422,"y":302,"direction":1},{"name":"Node","x":422,"y":332,"direction":0},{"name":"Node","x":422,"y":362,"direction":0},{"name":"Node","x":422,"y":392,"direction":0},{"name":"Node","x":422,"y":422,"direction":0},{"name":"Node","x":422,"y":452,"direction":0},{"name":"Node","x":422,"y":482,"direction":0},{"name":"Node","x":422,"y":512,"direction":0},{"name":"Node","x":422,"y":542,"direction":0},{"name":"Node","x":422,"y":572,"direction":0},{"name":"Node","x":452,"y":2,"direction":0},{"name":"Node","x":452,"y":32,"direction":1},{"name":"Node","x":452,"y":62,"direction":0},{"name":"Node","x":452,"y":92,"direction":0},{"name":"Node","x":452,"y":122,"direction":0},{"name":"Node","x":452,"y":152,"direction":0},{"name":"Node","x":452,"y":182,"direction":0},{"name":"Node","x":452,"y":212,"direction":0},{"name":"Node","x":452,"y":242,"direction":0},{"name":"Node","x":452,"y":272,"direction":2},{"name":"Node","x":452,"y":302,"direction":1},{"name":"Node","x":452,"y":332,"direction":0},{"name":"Node","x":452,"y":362,"direction":0},{"name":"Node","x":452,"y":392,"direction":0},{"name":"Node","x":452,"y":422,"direction":0},{"name":"Node","x":452,"y":452,"direction":0},{"name":"Node","x":452,"y":482,"direction":0},{"name":"Node","x":452,"y":512,"direction":0},{"name":"Node","x":452,"y":542,"direction":0},{"name":"Node","x":452,"y":572,"direction":0},{"name":"Node","x":482,"y":2,"direction":0},{"name":"Node","x":482,"y":32,"direction":1},{"name":"Node","x":482,"y":62,"direction":0},{"name":"Node","x":482,"y":92,"direction":0},{"name":"Node","x":482,"y":122,"direction":0},{"name":"Node","x":482,"y":152,"direction":0},{"name":"Node","x":482,"y":182,"direction":0},{"name":"Node","x":482,"y":212,"direction":0},{"name":"Node","x":482,"y":242,"direction":0},{"name":"Node","x":482,"y":272,"direction":2},{"name":"Node","x":482,"y":302,"direction":1},{"name":"Node","x":482,"y":332,"direction":0},{"name":"Node","x":482,"y":362,"direction":0},{"name":"Node","x":482,"y":392,"direction":0},{"name":"Node","x":482,"y":422,"direction":0},{"name":"Node","x":482,"y":452,"direction":0},{"name":"Node","x":482,"y":482,"direction":0},{"name":"Node","x":482,"y":512,"direction":0},{"name":"Node","x":482,"y":542,"direction":0},{"name":"Node","x":482,"y":572,"direction":0},{"name":"Node","x":512,"y":2,"direction":0},{"name":"Node","x":512,"y":32,"direction":1},{"name":"Node","x":512,"y":62,"direction":0},{"name":"Node","x":512,"y":92,"direction":0},{"name":"Node","x":512,"y":122,"direction":0},{"name":"Node","x":512,"y":152,"direction":0},{"name":"Node","x":512,"y":182,"direction":0},{"name":"Node","x":512,"y":212,"direction":0},{"name":"Node","x":512,"y":242,"direction":0},{"name":"Node","x":512,"y":272,"direction":2},{"name":"Node","x":512,"y":302,"direction":1},{"name":"Node","x":512,"y":332,"direction":0},{"name":"Node","x":512,"y":362,"direction":0},{"name":"Node","x":512,"y":392,"direction":0},{"name":"Node","x":512,"y":422,"direction":0},{"name":"Node","x":512,"y":452,"direction":0},{"name":"Node","x":512,"y":482,"direction":0},{"name":"Node","x":512,"y":512,"direction":0},{"name":"Node","x":512,"y":542,"direction":0},{"name":"Node","x":512,"y":572,"direction":0},{"name":"Node","x":542,"y":2,"direction":0},{"name":"Node","x":542,"y":32,"direction":1},{"name":"Node","x":542,"y":62,"direction":0},{"name":"Node","x":542,"y":92,"direction":0},{"name":"Node","x":542,"y":122,"direction":0},{"name":"Node","x":542,"y":152,"direction":0},{"name":"Node","x":542,"y":182,"direction":0},{"name":"Node","x":542,"y":212,"direction":0},{"name":"Node","x":542,"y":242,"direction":0},{"name":"Node","x":542,"y":272,"direction":2},{"name":"Node","x":542,"y":302,"direction":1},{"name":"Node","x":542,"y":332,"direction":0},{"name":"Node","x":542,"y":362,"direction":0},{"name":"Node","x":542,"y":392,"direction":0},{"name":"Node","x":542,"y":422,"direction":0},{"name":"Node","x":542,"y":452,"direction":0},{"name":"Node","x":542,"y":482,"direction":0},{"name":"Node","x":542,"y":512,"direction":0},{"name":"Node","x":542,"y":542,"direction":6},{"name":"Node","x":542,"y":572,"direction":0},{"name":"Node","x":572,"y":2,"direction":0},{"name":"Node","x":572,"y":32,"direction":1},{"name":"Node","x":572,"y":62,"direction":0},{"name":"Node","x":572,"y":92,"direction":0},{"name":"Node","x":572,"y":122,"direction":0},{"name":"Node","x":572,"y":152,"direction":0},{"name":"Node","x":572,"y":182,"direction":0},{"name":"Node","x":572,"y":212,"direction":0},{"name":"Node","x":572,"y":242,"direction":0},{"name":"Node","x":572,"y":272,"direction":2},{"name":"Node","x":572,"y":302,"direction":1},{"name":"Node","x":572,"y":332,"direction":0},{"name":"Node","x":572,"y":362,"direction":0},{"name":"Node","x":572,"y":392,"direction":0},{"name":"Node","x":572,"y":422,"direction":0},{"name":"Node","x":572,"y":452,"direction":0},{"name":"Node","x":572,"y":482,"direction":0},{"name":"Node","x":572,"y":512,"direction":0},{"name":"Node","x":572,"y":542,"direction":0},{"name":"Node","x":572,"y":572,"direction":0},{"name":"Node","x":602,"y":2,"direction":0},{"name":"Node","x":602,"y":32,"direction":1},{"name":"Node","x":602,"y":62,"direction":4},{"name":"Node","x":602,"y":92,"direction":4},{"name":"Node","x":602,"y":122,"direction":4},{"name":"Node","x":602,"y":152,"direction":4},{"name":"Node","x":602,"y":182,"direction":4},{"name":"Node","x":602,"y":212,"direction":4},{"name":"Node","x":602,"y":242,"direction":4},{"name":"Node","x":602,"y":272,"direction":2},{"name":"Node","x":602,"y":302,"direction":1},{"name":"Node","x":602,"y":332,"direction":0},{"name":"Node","x":602,"y":362,"direction":0},{"name":"Node","x":602,"y":392,"direction":0},{"name":"Node","x":602,"y":422,"direction":0},{"name":"Node","x":602,"y":452,"direction":0},{"name":"Node","x":602,"y":482,"direction":0},{"name":"Node","x":602,"y":512,"direction":0},{"name":"Node","x":602,"y":542,"direction":0},{"name":"Node","x":602,"y":572,"direction":0},{"name":"Node","x":632,"y":2,"direction":0},{"name":"Node","x":632,"y":32,"direction":1},{"name":"Node","x":632,"y":62,"direction":0},{"name":"Node","x":632,"y":92,"direction":0},{"name":"Node","x":632,"y":122,"direction":0},{"name":"Node","x":632,"y":152,"direction":0},{"name":"Node","x":632,"y":182,"direction":0},{"name":"Node","x":632,"y":212,"direction":0},{"name":"Node","x":632,"y":242,"direction":0},{"name":"Node","x":632,"y":272,"direction":2},{"name":"Node","x":632,"y":302,"direction":1},{"name":"Node","x":632,"y":332,"direction":0},{"name":"Node","x":632,"y":362,"direction":0},{"name":"Node","x":632,"y":392,"direction":0},{"name":"Node","x":632,"y":422,"direction":0},{"name":"Node","x":632,"y":452,"direction":0},{"name":"Node","x":632,"y":482,"direction":0},{"name":"Node","x":632,"y":512,"direction":0},{"name":"Node","x":632,"y":542,"direction":0},{"name":"Node","x":632,"y":572,"direction":0},{"name":"Node","x":662,"y":2,"direction":0},{"name":"Node","x":662,"y":32,"direction":1},{"name":"Node","x":662,"y":62,"direction":0},{"name":"Node","x":662,"y":92,"direction":0},{"name":"Node","x":662,"y":122,"direction":0},{"name":"Node","x":662,"y":152,"direction":0},{"name":"Node","x":662,"y":182,"direction":0},{"name":"Node","x":662,"y":212,"direction":0},{"name":"Node","x":662,"y":242,"direction":0},{"name":"Node","x":662,"y":272,"direction":2},{"name":"Node","x":662,"y":302,"direction":1},{"name":"Node","x":662,"y":332,"direction":0},{"name":"Node","x":662,"y":362,"direction":0},{"name":"Node","x":662,"y":392,"direction":0},{"name":"Node","x":662,"y":422,"direction":0},{"name":"Node","x":662,"y":452,"direction":0},{"name":"Node","x":662,"y":482,"direction":0},{"name":"Node","x":662,"y":512,"direction":0},{"name":"Node","x":662,"y":542,"direction":0},{"name":"Node","x":662,"y":572,"direction":0},{"name":"Node","x":692,"y":2,"direction":0},{"name":"Node","x":692,"y":32,"direction":1},{"name":"Node","x":692,"y":62,"direction":0},{"name":"Node","x":692,"y":92,"direction":0},{"name":"Node","x":692,"y":122,"direction":0},{"name":"Node","x":692,"y":152,"direction":0},{"name":"Node","x":692,"y":182,"direction":0},{"name":"Node","x":692,"y":212,"direction":0},{"name":"Node","x":692,"y":242,"direction":0},{"name":"Node","x":692,"y":272,"direction":2},{"name":"Node","x":692,"y":302,"direction":1},{"name":"Node","x":692,"y":332,"direction":0},{"name":"Node","x":692,"y":362,"direction":0},{"name":"Node","x":692,"y":392,"direction":0},{"name":"Node","x":692,"y":422,"direction":0},{"name":"Node","x":692,"y":452,"direction":0},{"name":"Node","x":692,"y":482,"direction":0},{"name":"Node","x":692,"y":512,"direction":0},{"name":"Node","x":692,"y":542,"direction":0},{"name":"Node","x":692,"y":572,"direction":0},{"name":"Node","x":722,"y":2,"direction":0},{"name":"Node","x":722,"y":32,"direction":1},{"name":"Node","x":722,"y":62,"direction":0},{"name":"Node","x":722,"y":92,"direction":0},{"name":"Node","x":722,"y":122,"direction":0},{"name":"Node","x":722,"y":152,"direction":0},{"name":"Node","x":722,"y":182,"direction":0},{"name":"Node","x":722,"y":212,"direction":0},{"name":"Node","x":722,"y":242,"direction":0},{"name":"Node","x":722,"y":272,"direction":2},{"name":"Node","x":722,"y":302,"direction":1},{"name":"Node","x":722,"y":332,"direction":0},{"name":"Node","x":722,"y":362,"direction":0},{"name":"Node","x":722,"y":392,"direction":0},{"name":"Node","x":722,"y":422,"direction":0},{"name":"Node","x":722,"y":452,"direction":0},{"name":"Node","x":722,"y":482,"direction":0},{"name":"Node","x":722,"y":512,"direction":0},{"name":"Node","x":722,"y":542,"direction":0},{"name":"Node","x":722,"y":572,"direction":0},{"name":"Node","x":752,"y":2,"direction":0},{"name":"Node","x":752,"y":32,"direction":1},{"name":"Node","x":752,"y":62,"direction":0},{"name":"Node","x":752,"y":92,"direction":0},{"name":"Node","x":752,"y":122,"direction":0},{"name":"Node","x":752,"y":152,"direction":0},{"name":"Node","x":752,"y":182,"direction":0},{"name":"Node","x":752,"y":212,"direction":0},{"name":"Node","x":752,"y":242,"direction":0},{"name":"Node","x":752,"y":272,"direction":2},{"name":"Node","x":752,"y":302,"direction":1},{"name":"Node","x":752,"y":332,"direction":0},{"name":"Node","x":752,"y":362,"direction":0},{"name":"Node","x":752,"y":392,"direction":0},{"name":"Node","x":752,"y":422,"direction":0},{"name":"Node","x":752,"y":452,"direction":0},{"name":"Node","x":752,"y":482,"direction":0},{"name":"Node","x":752,"y":512,"direction":0},{"name":"Node","x":752,"y":542,"direction":0},{"name":"Node","x":752,"y":572,"direction":0},{"name":"Node","x":782,"y":2,"direction":0},{"name":"Node","x":782,"y":32,"direction":1},{"name":"Node","x":782,"y":62,"direction":0},{"name":"Node","x":782,"y":92,"direction":0},{"name":"Node","x":782,"y":122,"direction":0},{"name":"Node","x":782,"y":152,"direction":0},{"name":"Node","x":782,"y":182,"direction":0},{"name":"Node","x":782,"y":212,"direction":0},{"name":"Node","x":782,"y":242,"direction":0},{"name":"Node","x":782,"y":272,"direction":2},{"name":"Node","x":782,"y":302,"direction":1},{"name":"Node","x":782,"y":332,"direction":0},{"name":"Node","x":782,"y":362,"direction":0},{"name":"Node","x":782,"y":392,"direction":0},{"name":"Node","x":782,"y":422,"direction":0},{"name":"Node","x":782,"y":452,"direction":0},{"name":"Node","x":782,"y":482,"direction":0},{"name":"Node","x":782,"y":512,"direction":0},{"name":"Node","x":782,"y":542,"direction":0},{"name":"Node","x":782,"y":572,"direction":0},{"name":"Node","x":812,"y":2,"direction":0},{"name":"Node","x":812,"y":32,"direction":1},{"name":"Node","x":812,"y":62,"direction":0},{"name":"Node","x":812,"y":92,"direction":0},{"name":"Node","x":812,"y":122,"direction":0},{"name":"Node","x":812,"y":152,"direction":0},{"name":"Node","x":812,"y":182,"direction":0},{"name":"Node","x":812,"y":212,"direction":0},{"name":"Node","x":812,"y":242,"direction":0},{"name":"Node","x":812,"y":272,"direction":2},{"name":"Node","x":812,"y":302,"direction":1},{"name":"Node","x":812,"y":332,"direction":0},{"name":"Node","x":812,"y":362,"direction":0},{"name":"Node","x":812,"y":392,"direction":0},{"name":"Node","x":812,"y":422,"direction":0},{"name":"Node","x":812,"y":452,"direction":0},{"name":"Node","x":812,"y":482,"direction":0},{"name":"Node","x":812,"y":512,"direction":0},{"name":"Node","x":812,"y":542,"direction":0},{"name":"Node","x":812,"y":572,"direction":0},{"name":"Node","x":842,"y":2,"direction":0},{"name":"Node","x":842,"y":32,"direction":1},{"name":"Node","x":842,"y":62,"direction":0},{"name":"Node","x":842,"y":92,"direction":0},{"name":"Node","x":842,"y":122,"direction":0},{"name":"Node","x":842,"y":152,"direction":0},{"name":"Node","x":842,"y":182,"direction":0},{"name":"Node","x":842,"y":212,"direction":0},{"name":"Node","x":842,"y":242,"direction":0},{"name":"Node","x":842,"y":272,"direction":2},{"name":"Node","x":842,"y":302,"direction":1},{"name":"Node","x":842,"y":332,"direction":0},{"name":"Node","x":842,"y":362,"direction":0},{"name":"Node","x":842,"y":392,"direction":0},{"name":"Node","x":842,"y":422,"direction":0},{"name":"Node","x":842,"y":452,"direction":0},{"name":"Node","x":842,"y":482,"direction":0},{"name":"Node","x":842,"y":512,"direction":0},{"name":"Node","x":842,"y":542,"direction":0},{"name":"Node","x":842,"y":572,"direction":0},{"name":"Node","x":872,"y":2,"direction":0},{"name":"Node","x":872,"y":32,"direction":1},{"name":"Node","x":872,"y":62,"direction":0},{"name":"Node","x":872,"y":92,"direction":0},{"name":"Node","x":872,"y":122,"direction":0},{"name":"Node","x":872,"y":152,"direction":0},{"name":"Node","x":872,"y":182,"direction":0},{"name":"Node","x":872,"y":212,"direction":0},{"name":"Node","x":872,"y":242,"direction":0},{"name":"Node","x":872,"y":272,"direction":2},{"name":"Node","x":872,"y":302,"direction":1},{"name":"Node","x":872,"y":332,"direction":0},{"name":"Node","x":872,"y":362,"direction":0},{"name":"Node","x":872,"y":392,"direction":0},{"name":"Node","x":872,"y":422,"direction":0},{"name":"Node","x":872,"y":452,"direction":0},{"name":"Node","x":872,"y":482,"direction":0},{"name":"Node","x":872,"y":512,"direction":0},{"name":"Node","x":872,"y":542,"direction":0},{"name":"Node","x":872,"y":572,"direction":0},{"name":"Node","x":902,"y":2,"direction":0},{"name":"Node","x":902,"y":32,"direction":1},{"name":"Node","x":902,"y":62,"direction":0},{"name":"Node","x":902,"y":92,"direction":0},{"name":"Node","x":902,"y":122,"direction":0},{"name":"Node","x":902,"y":152,"direction":0},{"name":"Node","x":902,"y":182,"direction":0},{"name":"Node","x":902,"y":212,"direction":0},{"name":"Node","x":902,"y":242,"direction":0},{"name":"Node","x":902,"y":272,"direction":2},{"name":"Node","x":902,"y":302,"direction":1},{"name":"Node","x":902,"y":332,"direction":0},{"name":"Node","x":902,"y":362,"direction":0},{"name":"Node","x":902,"y":392,"direction":0},{"name":"Node","x":902,"y":422,"direction":0},{"name":"Node","x":902,"y":452,"direction":0},{"name":"Node","x":902,"y":482,"direction":0},{"name":"Node","x":902,"y":512,"direction":0},{"name":"Node","x":902,"y":542,"direction":0},{"name":"Node","x":902,"y":572,"direction":0},{"name":"Node","x":932,"y":2,"direction":0},{"name":"Node","x":932,"y":32,"direction":1},{"name":"Node","x":932,"y":62,"direction":0},{"name":"Node","x":932,"y":92,"direction":0},{"name":"Node","x":932,"y":122,"direction":0},{"name":"Node","x":932,"y":152,"direction":0},{"name":"Node","x":932,"y":182,"direction":0},{"name":"Node","x":932,"y":212,"direction":0},{"name":"Node","x":932,"y":242,"direction":0},{"name":"Node","x":932,"y":272,"direction":2},{"name":"Node","x":932,"y":302,"direction":1},{"name":"Node","x":932,"y":332,"direction":0},{"name":"Node","x":932,"y":362,"direction":0},{"name":"Node","x":932,"y":392,"direction":0},{"name":"Node","x":932,"y":422,"direction":0},{"name":"Node","x":932,"y":452,"direction":0},{"name":"Node","x":932,"y":482,"direction":0},{"name":"Node","x":932,"y":512,"direction":0},{"name":"Node","x":932,"y":542,"direction":0},{"name":"Node","x":932,"y":572,"direction":0},{"name":"Node","x":962,"y":2,"direction":0},{"name":"Node","x":962,"y":32,"direction":1},{"name":"Node","x":962,"y":62,"direction":0},{"name":"Node","x":962,"y":92,"direction":0},{"name":"Node","x":962,"y":122,"direction":0},{"name":"Node","x":962,"y":152,"direction":0},{"name":"Node","x":962,"y":182,"direction":0},{"name":"Node","x":962,"y":212,"direction":0},{"name":"Node","x":962,"y":242,"direction":0},{"name":"Node","x":962,"y":272,"direction":2},{"name":"Node","x":962,"y":302,"direction":1},{"name":"Node","x":962,"y":332,"direction":0},{"name":"Node","x":962,"y":362,"direction":0},{"name":"Node","x":962,"y":392,"direction":0},{"name":"Node","x":962,"y":422,"direction":0},{"name":"Node","x":962,"y":452,"direction":0},{"name":"Node","x":962,"y":482,"direction":0},{"name":"Node","x":962,"y":512,"direction":0},{"name":"Node","x":962,"y":542,"direction":0},{"name":"Node","x":962,"y":572,"direction":0},{"name":"Node","x":992,"y":2,"direction":0},{"name":"Node","x":992,"y":32,"direction":4},{"name":"Node","x":992,"y":62,"direction":4},{"name":"Node","x":992,"y":92,"direction":4},{"name":"Node","x":992,"y":122,"direction":4},{"name":"Node","x":992,"y":152,"direction":4},{"name":"Node","x":992,"y":182,"direction":4},{"name":"Node","x":992,"y":212,"direction":4},{"name":"Node","x":992,"y":242,"direction":4},{"name":"Node","x":992,"y":272,"direction":2},{"name":"Node","x":992,"y":302,"direction":1},{"name":"Node","x":992,"y":332,"direction":0},{"name":"Node","x":992,"y":362,"direction":0},{"name":"Node","x":992,"y":392,"direction":0},{"name":"Node","x":992,"y":422,"direction":0},{"name":"Node","x":992,"y":452,"direction":0},{"name":"Node","x":992,"y":482,"direction":0},{"name":"Node","x":992,"y":512,"direction":0},{"name":"Node","x":992,"y":542,"direction":6},{"name":"Node","x":992,"y":572,"direction":0},{"name":"Node","x":1022,"y":2,"direction":0},{"name":"Node","x":1022,"y":32,"direction":0},{"name":"Node","x":1022,"y":62,"direction":0},{"name":"Node","x":1022,"y":92,"direction":0},{"name":"Node","x":1022,"y":122,"direction":0},{"name":"Node","x":1022,"y":152,"direction":0},{"name":"Node","x":1022,"y":182,"direction":0},{"name":"Node","x":1022,"y":212,"direction":0},{"name":"Node","x":1022,"y":242,"direction":0},{"name":"Node","x":1022,"y":272,"direction":0},{"name":"Node","x":1022,"y":302,"direction":0},{"name":"Node","x":1022,"y":332,"direction":0},{"name":"Node","x":1022,"y":362,"direction":0},{"name":"Node","x":1022,"y":392,"direction":0},{"name":"Node","x":1022,"y":422,"direction":0},{"name":"Node","x":1022,"y":452,"direction":0},{"name":"Node","x":1022,"y":482,"direction":0},{"name":"Node","x":1022,"y":512,"direction":0},{"name":"Node","x":1022,"y":542,"direction":0},{"name":"Node","x":1022,"y":572,"direction":0},{"name":"Node","x":1052,"y":2,"direction":0},{"name":"Node","x":1052,"y":32,"direction":0},{"name":"Node","x":1052,"y":62,"direction":0},{"name":"Node","x":1052,"y":92,"direction":0},{"name":"Node","x":1052,"y":122,"direction":0},{"name":"Node","x":1052,"y":152,"direction":0},{"name":"Node","x":1052,"y":182,"direction":0},{"name":"Node","x":1052,"y":212,"direction":0},{"name":"Node","x":1052,"y":242,"direction":0},{"name":"Node","x":1052,"y":272,"direction":0},{"name":"Node","x":1052,"y":302,"direction":0},{"name":"Node","x":1052,"y":332,"direction":0},{"name":"Node","x":1052,"y":362,"direction":0},{"name":"Node","x":1052,"y":392,"direction":0},{"name":"Node","x":1052,"y":422,"direction":0},{"name":"Node","x":1052,"y":452,"direction":0},{"name":"Node","x":1052,"y":482,"direction":0},{"name":"Node","x":1052,"y":512,"direction":0},{"name":"Node","x":1052,"y":542,"direction":0},{"name":"Node","x":1052,"y":572,"direction":0},{"name":"Node","x":1082,"y":2,"direction":0},{"name":"Node","x":1082,"y":32,"direction":0},{"name":"Node","x":1082,"y":62,"direction":0},{"name":"Node","x":1082,"y":92,"direction":0},{"name":"Node","x":1082,"y":122,"direction":0},{"name":"Node","x":1082,"y":152,"direction":0},{"name":"Node","x":1082,"y":182,"direction":0},{"name":"Node","x":1082,"y":212,"direction":0},{"name":"Node","x":1082,"y":242,"direction":0},{"name":"Node","x":1082,"y":272,"direction":0},{"name":"Node","x":1082,"y":302,"direction":0},{"name":"Node","x":1082,"y":332,"direction":0},{"name":"Node","x":1082,"y":362,"direction":0},{"name":"Node","x":1082,"y":392,"direction":0},{"name":"Node","x":1082,"y":422,"direction":0},{"name":"Node","x":1082,"y":452,"direction":0},{"name":"Node","x":1082,"y":482,"direction":0},{"name":"Node","x":1082,"y":512,"direction":0},{"name":"Node","x":1082,"y":542,"direction":0},{"name":"Node","x":1082,"y":572,"direction":0},{"name":"Node","x":1112,"y":2,"direction":0},{"name":"Node","x":1112,"y":32,"direction":0},{"name":"Node","x":1112,"y":62,"direction":0},{"name":"Node","x":1112,"y":92,"direction":0},{"name":"Node","x":1112,"y":122,"direction":0},{"name":"Node","x":1112,"y":152,"direction":0},{"name":"Node","x":1112,"y":182,"direction":0},{"name":"Node","x":1112,"y":212,"direction":0},{"name":"Node","x":1112,"y":242,"direction":0},{"name":"Node","x":1112,"y":272,"direction":0},{"name":"Node","x":1112,"y":302,"direction":0},{"name":"Node","x":1112,"y":332,"direction":0},{"name":"Node","x":1112,"y":362,"direction":0},{"name":"Node","x":1112,"y":392,"direction":0},{"name":"Node","x":1112,"y":422,"direction":0},{"name":"Node","x":1112,"y":452,"direction":0},{"name":"Node","x":1112,"y":482,"direction":0},{"name":"Node","x":1112,"y":512,"direction":0},{"name":"Node","x":1112,"y":542,"direction":0},{"name":"Node","x":1112,"y":572,"direction":0},{"name":"Node","x":1142,"y":2,"direction":0},{"name":"Node","x":1142,"y":32,"direction":0},{"name":"Node","x":1142,"y":62,"direction":0},{"name":"Node","x":1142,"y":92,"direction":0},{"name":"Node","x":1142,"y":122,"direction":0},{"name":"Node","x":1142,"y":152,"direction":0},{"name":"Node","x":1142,"y":182,"direction":0},{"name":"Node","x":1142,"y":212,"direction":0},{"name":"Node","x":1142,"y":242,"direction":0},{"name":"Node","x":1142,"y":272,"direction":0},{"name":"Node","x":1142,"y":302,"direction":0},{"name":"Node","x":1142,"y":332,"direction":0},{"name":"Node","x":1142,"y":362,"direction":0},{"name":"Node","x":1142,"y":392,"direction":0},{"name":"Node","x":1142,"y":422,"direction":0},{"name":"Node","x":1142,"y":452,"direction":0},{"name":"Node","x":1142,"y":482,"direction":0},{"name":"Node","x":1142,"y":512,"direction":0},{"name":"Node","x":1142,"y":542,"direction":0},{"name":"Node","x":1142,"y":572,"direction":0},{"name":"Node","x":1172,"y":2,"direction":0},{"name":"Node","x":1172,"y":32,"direction":0},{"name":"Node","x":1172,"y":62,"direction":0},{"name":"Node","x":1172,"y":92,"direction":0},{"name":"Node","x":1172,"y":122,"direction":0},{"name":"Node","x":1172,"y":152,"direction":0},{"name":"Node","x":1172,"y":182,"direction":0},{"name":"Node","x":1172,"y":212,"direction":0},{"name":"Node","x":1172,"y":242,"direction":0},{"name":"Node","x":1172,"y":272,"direction":0},{"name":"Node","x":1172,"y":302,"direction":0},{"name":"Node","x":1172,"y":332,"direction":0},{"name":"Node","x":1172,"y":362,"direction":0},{"name":"Node","x":1172,"y":392,"direction":0},{"name":"Node","x":1172,"y":422,"direction":0},{"name":"Node","x":1172,"y":452,"direction":0},{"name":"Node","x":1172,"y":482,"direction":0},{"name":"Node","x":1172,"y":512,"direction":0},{"name":"Node","x":1172,"y":542,"direction":0},{"name":"Node","x":1172,"y":572,"direction":0}]